terraso_allauth/__init__.py
terraso_allauth/provider.py
terraso_allauth/urls.py
terraso_allauth/views.py
terraso_allauth-2.0.0.dist-info/METADATA
terraso_allauth-2.0.0.dist-info/WHEEL
terraso_allauth-2.0.0.dist-info/top_level.txt
terraso_allauth-2.0.0.dist-info/RECORD
