Metadata-Version: 2.1
Name: terraso-allauth
Version: 2.0.0
Summary: A Django app to plug Terraso as a provider to django-allauth.
Home-page: https://www.github.com/techmatters/terraso-allauth
Author: Terraso Developers
Author-email: info@terraso.org
License: AGPL-3
Project-URL: Bug Tracker, https://www.github.com/techmatters/terraso-allauth/issues
Classifier: Environment :: Web Environment
Classifier: Framework :: Django
Classifier: Intended Audience :: Developers
Classifier: License :: OSI Approved :: GNU Affero General Public License v3
Classifier: Operating System :: OS Independent
Classifier: Programming Language :: Python
Classifier: Programming Language :: Python :: 3
Classifier: Programming Language :: Python :: 3 :: Only
Classifier: Programming Language :: Python :: 3.8
Classifier: Programming Language :: Python :: 3.9
Classifier: Programming Language :: Python :: 3.10
Classifier: Topic :: Internet :: WWW/HTTP
Classifier: Topic :: Internet :: WWW/HTTP :: Dynamic Content
Requires-Python: >=3.8
